cocomltools/__init__.py
cocomltools/cmd.py
cocomltools/coco_ops.py
cocomltools/logger.py
cocomltools/main_cli.py
cocomltools/models/base.py
cocomltools/models/coco.py
cocomltools/utils.py
cocomltools-0.1.8.dist-info/METADATA
cocomltools-0.1.8.dist-info/WHEEL
cocomltools-0.1.8.dist-info/entry_points.txt
cocomltools-0.1.8.dist-info/RECORD
