Metadata-Version: 2.1
Name: cocomltools
Version: 0.1.8
Summary: 
Author: Ghallabi
Author-email: ghallabi.farouk@gmail.com
Requires-Python: >=3.9.8,<4.0.0
Classifier: Programming Language :: Python :: 3
Classifier: Programming Language :: Python :: 3.10
Classifier: Programming Language :: Python :: 3.11
Classifier: Programming Language :: Python :: 3.12
Classifier: Programming Language :: Python :: 3.13
Requires-Dist: numpy (>=1.26.0,<2.0.0)
Requires-Dist: pillow (>=10.4.0,<11.0.0)
Requires-Dist: pydantic (==2.8.2)
Requires-Dist: pydantic_core (==2.20.1)
Requires-Dist: rich (>=13.7.1,<14.0.0)
Requires-Dist: scikit-learn (>=1.5.1,<2.0.0)
Requires-Dist: scikit-multilearn (>=0.2.0,<0.3.0)
